Metadata-Version: 2.2
Name: topsis_102203427
Version: 1.0.2
Summary: A Python package for implementing TOPSIS (Technique for Order of Preference by Similarity to Ideal Solution).
Home-page: https://github.com/Aditya-prog-git/TopsisPackage.git
Author: Aditya Raj Singh
Author-email: aditya003rs@gmail.com
Classifier: Programming Language :: Python :: 3
Classifier: Operating System :: OS Independent
Requires-Python: >=3.6
Requires-Dist: pandas>=1.0.0
Requires-Dist: numpy>=1.19.0
Dynamic: author
Dynamic: author-email
Dynamic: classifier
Dynamic: description
Dynamic: description-content-type
Dynamic: home-page
Dynamic: requires-dist
Dynamic: requires-python
Dynamic: summary
